{
  "batchId": "batch-2",
  "processedDate": "2025-09-10T13:56:43.904Z",
  "resourceCount": 10,
  "enhancedCount": 10,
  "resources": [
    {
      "id": "resource-00011",
      "title": "Year 11 Social Studies: Resource 11",
      "subject": "Social Studies",
      "yearLevel": "Year 11",
      "type": "activity",
      "description": "Comprehensive activity for Year 11 Social Studies learning",
      "culturalElements": 1,
      "currentPass": 4,
      "originalQuality": 6.487616522901497,
      "enhancement": {
        "passesCompleted": 4,
        "culturalAuthenticity": 8.948259853538143,
        "pedagogicalDepth": 8.654075842316285,
        "progressiveIndex": 9.011204542098175,
        "qualityScore": 13.910443080420519,
        "passes": [
          {
            "passNumber": 1,
            "kaiako": "Whaea Aroha Kaitiaki-ā-Taonga",
            "specialization": "Cultural Authenticity",
            "enhancedContent": {
              "focus": "Cultural authenticity",
              "elements": [
                "karakia",
                "tikanga",
                "Te Reo"
              ]
            },
            "timeCompleted": "2025-09-10T13:56:43.904Z",
            "qualityImprovement": 2.039681059582964
          },
          {
            "passNumber": 2,
            "kaiako": "Matua Rangi Akoranga-Hou",
            "specialization": "Progressive Pedagogy",
            "enhancedContent": {
              "focus": "Progressive pedagogy",
              "elements": [
                "project-based",
                "student-agency",
                "design-thinking"
              ]
            },
            "timeCompleted": "2025-09-10T13:56:43.904Z",
            "qualityImprovement": 1.8751134470310693
          },
          {
            "passNumber": 3,
            "kaiako": "Whaea Mere Ako-Katoa",
            "specialization": "Universal Design",
            "enhancedContent": {
              "focus": "Universal design",
              "elements": [
                "multi-modal",
                "accessible",
                "inclusive"
              ]
            },
            "timeCompleted": "2025-09-10T13:56:43.904Z",
            "qualityImprovement": 1.683774675289874
          },
          {
            "passNumber": 4,
            "kaiako": "Matua Tane Aromatawai-Tika",
            "specialization": "Assessment Innovation",
            "enhancedContent": {
              "focus": "Assessment innovation",
              "elements": [
                "portfolio",
                "authentic",
                "growth-mindset"
              ]
            },
            "timeCompleted": "2025-09-10T13:56:43.904Z",
            "qualityImprovement": 1.8242573756151155
          }
        ]
      },
      "metadata": {
        "created": "2023-06-03T12:00:00.000Z",
        "lastModified": "2025-09-10T13:56:43.903Z",
        "tags": [
          "social-studies",
          "year-11"
        ],
        "difficulty": 3,
        "estimatedDuration": 79
      }
    },
    {
      "id": "resource-00012",
      "title": "Year 13 Social Studies: Resource 12",
      "subject": "Social Studies",
      "yearLevel": "Year 13",
      "type": "multimedia",
      "description": "Comprehensive multimedia for Year 13 Social Studies learning",
      "culturalElements": 1,
      "currentPass": 4,
      "originalQuality": 6.470644320705326,
      "enhancement": {
        "passesCompleted": 4,
        "culturalAuthenticity": 9.308500731288495,
        "pedagogicalDepth": 8.847658230511332,
        "progressiveIndex": 9.671430371649812,
        "qualityScore": 13.570670034515864,
        "passes": [
          {
            "passNumber": 1,
            "kaiako": "Whaea Aroha Kaitiaki-ā-Taonga",
            "specialization": "Cultural Authenticity",
            "enhancedContent": {
              "focus": "Cultural authenticity",
              "elements": [
                "karakia",
                "tikanga",
                "Te Reo"
              ]
            },
            "timeCompleted": "2025-09-10T13:56:43.904Z",
            "qualityImprovement": 2.2177190263878828
          },
          {
            "passNumber": 2,
            "kaiako": "Matua Rangi Akoranga-Hou",
            "specialization": "Progressive Pedagogy",
            "enhancedContent": {
              "focus": "Progressive pedagogy",
              "elements": [
                "project-based",
                "student-agency",
                "design-thinking"
              ]
            },
            "timeCompleted": "2025-09-10T13:56:43.904Z",
            "qualityImprovement": 1.815829514796515
          },
          {
            "passNumber": 3,
            "kaiako": "Whaea Mere Ako-Katoa",
            "specialization": "Universal Design",
            "enhancedContent": {
              "focus": "Universal design",
              "elements": [
                "multi-modal",
                "accessible",
                "inclusive"
              ]
            },
            "timeCompleted": "2025-09-10T13:56:43.904Z",
            "qualityImprovement": 1.6415941228889528
          },
          {
            "passNumber": 4,
            "kaiako": "Matua Tane Aromatawai-Tika",
            "specialization": "Assessment Innovation",
            "enhancedContent": {
              "focus": "Assessment innovation",
              "elements": [
                "portfolio",
                "authentic",
                "growth-mindset"
              ]
            },
            "timeCompleted": "2025-09-10T13:56:43.904Z",
            "qualityImprovement": 1.4248830497371858
          }
        ]
      },
      "metadata": {
        "created": "2023-12-03T11:00:00.000Z",
        "lastModified": "2025-09-10T13:56:43.903Z",
        "tags": [
          "social-studies",
          "year-13"
        ],
        "difficulty": 4,
        "estimatedDuration": 79
      }
    },
    {
      "id": "resource-00013",
      "title": "Year 11 Social Studies: Resource 13",
      "subject": "Social Studies",
      "yearLevel": "Year 11",
      "type": "lesson",
      "description": "Comprehensive lesson for Year 11 Social Studies learning",
      "culturalElements": 5,
      "currentPass": 4,
      "originalQuality": 6.596766779554765,
      "enhancement": {
        "passesCompleted": 4,
        "culturalAuthenticity": 9.227764085507301,
        "pedagogicalDepth": 9.362678853048658,
        "progressiveIndex": 9.777527071321963,
        "qualityScore": 14.301033054409597,
        "passes": [
          {
            "passNumber": 1,
            "kaiako": "Whaea Aroha Kaitiaki-ā-Taonga",
            "specialization": "Cultural Authenticity",
            "enhancedContent": {
              "focus": "Cultural authenticity",
              "elements": [
                "karakia",
                "tikanga",
                "Te Reo"
              ]
            },
            "timeCompleted": "2025-09-10T13:56:43.904Z",
            "qualityImprovement": 2.268479195845078
          },
          {
            "passNumber": 2,
            "kaiako": "Matua Rangi Akoranga-Hou",
            "specialization": "Progressive Pedagogy",
            "enhancedContent": {
              "focus": "Progressive pedagogy",
              "elements": [
                "project-based",
                "student-agency",
                "design-thinking"
              ]
            },
            "timeCompleted": "2025-09-10T13:56:43.904Z",
            "qualityImprovement": 2.1587543352514706
          },
          {
            "passNumber": 3,
            "kaiako": "Whaea Mere Ako-Katoa",
            "specialization": "Universal Design",
            "enhancedContent": {
              "focus": "Universal design",
              "elements": [
                "multi-modal",
                "accessible",
                "inclusive"
              ]
            },
            "timeCompleted": "2025-09-10T13:56:43.904Z",
            "qualityImprovement": 1.7547909460657434
          },
          {
            "passNumber": 4,
            "kaiako": "Matua Tane Aromatawai-Tika",
            "specialization": "Assessment Innovation",
            "enhancedContent": {
              "focus": "Assessment innovation",
              "elements": [
                "portfolio",
                "authentic",
                "growth-mindset"
              ]
            },
            "timeCompleted": "2025-09-10T13:56:43.904Z",
            "qualityImprovement": 1.5222417976925395
          }
        ]
      },
      "metadata": {
        "created": "2023-05-24T12:00:00.000Z",
        "lastModified": "2025-09-10T13:56:43.903Z",
        "tags": [
          "social-studies",
          "year-11"
        ],
        "difficulty": 4,
        "estimatedDuration": 145
      }
    },
    {
      "id": "resource-00014",
      "title": "Year 8 Social Studies: Resource 14",
      "subject": "Social Studies",
      "yearLevel": "Year 8",
      "type": "multimedia",
      "description": "Comprehensive multimedia for Year 8 Social Studies learning",
      "culturalElements": 4,
      "currentPass": 4,
      "originalQuality": 6.877310320485098,
      "enhancement": {
        "passesCompleted": 4,
        "culturalAuthenticity": 9.858755582468069,
        "pedagogicalDepth": 9.993997003556427,
        "progressiveIndex": 9.483225860040816,
        "qualityScore": 14.169725229482244,
        "passes": [
          {
            "passNumber": 1,
            "kaiako": "Whaea Aroha Kaitiaki-ā-Taonga",
            "specialization": "Cultural Authenticity",
            "enhancedContent": {
              "focus": "Cultural authenticity",
              "elements": [
                "karakia",
                "tikanga",
                "Te Reo"
              ]
            },
            "timeCompleted": "2025-09-10T13:56:43.904Z",
            "qualityImprovement": 2.160143440776179
          },
          {
            "passNumber": 2,
            "kaiako": "Matua Rangi Akoranga-Hou",
            "specialization": "Progressive Pedagogy",
            "enhancedContent": {
              "focus": "Progressive pedagogy",
              "elements": [
                "project-based",
                "student-agency",
                "design-thinking"
              ]
            },
            "timeCompleted": "2025-09-10T13:56:43.904Z",
            "qualityImprovement": 2.1449100394337623
          },
          {
            "passNumber": 3,
            "kaiako": "Whaea Mere Ako-Katoa",
            "specialization": "Universal Design",
            "enhancedContent": {
              "focus": "Universal design",
              "elements": [
                "multi-modal",
                "accessible",
                "inclusive"
              ]
            },
            "timeCompleted": "2025-09-10T13:56:43.904Z",
            "qualityImprovement": 1.5273721179451947
          },
          {
            "passNumber": 4,
            "kaiako": "Matua Tane Aromatawai-Tika",
            "specialization": "Assessment Innovation",
            "enhancedContent": {
              "focus": "Assessment innovation",
              "elements": [
                "portfolio",
                "authentic",
                "growth-mindset"
              ]
            },
            "timeCompleted": "2025-09-10T13:56:43.904Z",
            "qualityImprovement": 1.459989310842012
          }
        ]
      },
      "metadata": {
        "created": "2023-02-28T11:00:00.000Z",
        "lastModified": "2025-09-10T13:56:43.903Z",
        "tags": [
          "social-studies",
          "year-8"
        ],
        "difficulty": 4,
        "estimatedDuration": 81
      }
    },
    {
      "id": "resource-00015",
      "title": "Year 9 Social Studies: Resource 15",
      "subject": "Social Studies",
      "yearLevel": "Year 9",
      "type": "assessment",
      "description": "Comprehensive assessment for Year 9 Social Studies learning",
      "culturalElements": 1,
      "currentPass": 4,
      "originalQuality": 6.266575730516038,
      "enhancement": {
        "passesCompleted": 4,
        "culturalAuthenticity": 9.31809901038024,
        "pedagogicalDepth": 8.679851340363625,
        "progressiveIndex": 9.345953706633571,
        "qualityScore": 13.988002760138171,
        "passes": [
          {
            "passNumber": 1,
            "kaiako": "Whaea Aroha Kaitiaki-ā-Taonga",
            "specialization": "Cultural Authenticity",
            "enhancedContent": {
              "focus": "Cultural authenticity",
              "elements": [
                "karakia",
                "tikanga",
                "Te Reo"
              ]
            },
            "timeCompleted": "2025-09-10T13:56:43.904Z",
            "qualityImprovement": 2.14676523629219
          },
          {
            "passNumber": 2,
            "kaiako": "Matua Rangi Akoranga-Hou",
            "specialization": "Progressive Pedagogy",
            "enhancedContent": {
              "focus": "Progressive pedagogy",
              "elements": [
                "project-based",
                "student-agency",
                "design-thinking"
              ]
            },
            "timeCompleted": "2025-09-10T13:56:43.904Z",
            "qualityImprovement": 2.2690005250247234
          },
          {
            "passNumber": 3,
            "kaiako": "Whaea Mere Ako-Katoa",
            "specialization": "Universal Design",
            "enhancedContent": {
              "focus": "Universal design",
              "elements": [
                "multi-modal",
                "accessible",
                "inclusive"
              ]
            },
            "timeCompleted": "2025-09-10T13:56:43.904Z",
            "qualityImprovement": 1.8793286367317965
          },
          {
            "passNumber": 4,
            "kaiako": "Matua Tane Aromatawai-Tika",
            "specialization": "Assessment Innovation",
            "enhancedContent": {
              "focus": "Assessment innovation",
              "elements": [
                "portfolio",
                "authentic",
                "growth-mindset"
              ]
            },
            "timeCompleted": "2025-09-10T13:56:43.904Z",
            "qualityImprovement": 1.4263326315734228
          }
        ]
      },
      "metadata": {
        "created": "2023-11-29T11:00:00.000Z",
        "lastModified": "2025-09-10T13:56:43.903Z",
        "tags": [
          "social-studies",
          "year-9"
        ],
        "difficulty": 3,
        "estimatedDuration": 34
      }
    },
    {
      "id": "resource-00016",
      "title": "Year 10 Social Studies: Resource 16",
      "subject": "Social Studies",
      "yearLevel": "Year 10",
      "type": "unit-plan",
      "description": "Comprehensive unit-plan for Year 10 Social Studies learning",
      "culturalElements": 4,
      "currentPass": 4,
      "originalQuality": 5.9381614257308,
      "enhancement": {
        "passesCompleted": 4,
        "culturalAuthenticity": 8.511735814865894,
        "pedagogicalDepth": 9.012563758216947,
        "progressiveIndex": 9.916418727097817,
        "qualityScore": 13.333013288609537,
        "passes": [
          {
            "passNumber": 1,
            "kaiako": "Whaea Aroha Kaitiaki-ā-Taonga",
            "specialization": "Cultural Authenticity",
            "enhancedContent": {
              "focus": "Cultural authenticity",
              "elements": [
                "karakia",
                "tikanga",
                "Te Reo"
              ]
            },
            "timeCompleted": "2025-09-10T13:56:43.904Z",
            "qualityImprovement": 2.1078830198218164
          },
          {
            "passNumber": 2,
            "kaiako": "Matua Rangi Akoranga-Hou",
            "specialization": "Progressive Pedagogy",
            "enhancedContent": {
              "focus": "Progressive pedagogy",
              "elements": [
                "project-based",
                "student-agency",
                "design-thinking"
              ]
            },
            "timeCompleted": "2025-09-10T13:56:43.904Z",
            "qualityImprovement": 2.1000117686527187
          },
          {
            "passNumber": 3,
            "kaiako": "Whaea Mere Ako-Katoa",
            "specialization": "Universal Design",
            "enhancedContent": {
              "focus": "Universal design",
              "elements": [
                "multi-modal",
                "accessible",
                "inclusive"
              ]
            },
            "timeCompleted": "2025-09-10T13:56:43.904Z",
            "qualityImprovement": 1.726473681006019
          },
          {
            "passNumber": 4,
            "kaiako": "Matua Tane Aromatawai-Tika",
            "specialization": "Assessment Innovation",
            "enhancedContent": {
              "focus": "Assessment innovation",
              "elements": [
                "portfolio",
                "authentic",
                "growth-mindset"
              ]
            },
            "timeCompleted": "2025-09-10T13:56:43.904Z",
            "qualityImprovement": 1.460483393398183
          }
        ]
      },
      "metadata": {
        "created": "2023-03-08T11:00:00.000Z",
        "lastModified": "2025-09-10T13:56:43.903Z",
        "tags": [
          "social-studies",
          "year-10"
        ],
        "difficulty": 2,
        "estimatedDuration": 71
      }
    },
    {
      "id": "resource-00017",
      "title": "Year 13 Social Studies: Resource 17",
      "subject": "Social Studies",
      "yearLevel": "Year 13",
      "type": "multimedia",
      "description": "Comprehensive multimedia for Year 13 Social Studies learning",
      "culturalElements": 1,
      "currentPass": 4,
      "originalQuality": 6.570311598440092,
      "enhancement": {
        "passesCompleted": 4,
        "culturalAuthenticity": 9.636114673941265,
        "pedagogicalDepth": 9.868092107554602,
        "progressiveIndex": 9.480237882459972,
        "qualityScore": 14.283178568098405,
        "passes": [
          {
            "passNumber": 1,
            "kaiako": "Whaea Aroha Kaitiaki-ā-Taonga",
            "specialization": "Cultural Authenticity",
            "enhancedContent": {
              "focus": "Cultural authenticity",
              "elements": [
                "karakia",
                "tikanga",
                "Te Reo"
              ]
            },
            "timeCompleted": "2025-09-10T13:56:43.904Z",
            "qualityImprovement": 2.2840381394300056
          },
          {
            "passNumber": 2,
            "kaiako": "Matua Rangi Akoranga-Hou",
            "specialization": "Progressive Pedagogy",
            "enhancedContent": {
              "focus": "Progressive pedagogy",
              "elements": [
                "project-based",
                "student-agency",
                "design-thinking"
              ]
            },
            "timeCompleted": "2025-09-10T13:56:43.904Z",
            "qualityImprovement": 1.8315381551524808
          },
          {
            "passNumber": 3,
            "kaiako": "Whaea Mere Ako-Katoa",
            "specialization": "Universal Design",
            "enhancedContent": {
              "focus": "Universal design",
              "elements": [
                "multi-modal",
                "accessible",
                "inclusive"
              ]
            },
            "timeCompleted": "2025-09-10T13:56:43.904Z",
            "qualityImprovement": 1.8499937771071737
          },
          {
            "passNumber": 4,
            "kaiako": "Matua Tane Aromatawai-Tika",
            "specialization": "Assessment Innovation",
            "enhancedContent": {
              "focus": "Assessment innovation",
              "elements": [
                "portfolio",
                "authentic",
                "growth-mindset"
              ]
            },
            "timeCompleted": "2025-09-10T13:56:43.904Z",
            "qualityImprovement": 1.7472968979686505
          }
        ]
      },
      "metadata": {
        "created": "2023-09-29T11:00:00.000Z",
        "lastModified": "2025-09-10T13:56:43.904Z",
        "tags": [
          "social-studies",
          "year-13"
        ],
        "difficulty": 2,
        "estimatedDuration": 37
      }
    },
    {
      "id": "resource-00018",
      "title": "Year 11 Social Studies: Resource 18",
      "subject": "Social Studies",
      "yearLevel": "Year 11",
      "type": "assessment",
      "description": "Comprehensive assessment for Year 11 Social Studies learning",
      "culturalElements": 4,
      "currentPass": 4,
      "originalQuality": 6.640704115319069,
      "enhancement": {
        "passesCompleted": 4,
        "culturalAuthenticity": 9.039365777757428,
        "pedagogicalDepth": 9.715828289842133,
        "progressiveIndex": 8.876034765243448,
        "qualityScore": 14.144166967121615,
        "passes": [
          {
            "passNumber": 1,
            "kaiako": "Whaea Aroha Kaitiaki-ā-Taonga",
            "specialization": "Cultural Authenticity",
            "enhancedContent": {
              "focus": "Cultural authenticity",
              "elements": [
                "karakia",
                "tikanga",
                "Te Reo"
              ]
            },
            "timeCompleted": "2025-09-10T13:56:43.904Z",
            "qualityImprovement": 2.195011805262159
          },
          {
            "passNumber": 2,
            "kaiako": "Matua Rangi Akoranga-Hou",
            "specialization": "Progressive Pedagogy",
            "enhancedContent": {
              "focus": "Progressive pedagogy",
              "elements": [
                "project-based",
                "student-agency",
                "design-thinking"
              ]
            },
            "timeCompleted": "2025-09-10T13:56:43.904Z",
            "qualityImprovement": 2.1948660527168253
          },
          {
            "passNumber": 3,
            "kaiako": "Whaea Mere Ako-Katoa",
            "specialization": "Universal Design",
            "enhancedContent": {
              "focus": "Universal design",
              "elements": [
                "multi-modal",
                "accessible",
                "inclusive"
              ]
            },
            "timeCompleted": "2025-09-10T13:56:43.904Z",
            "qualityImprovement": 1.683769343395523
          },
          {
            "passNumber": 4,
            "kaiako": "Matua Tane Aromatawai-Tika",
            "specialization": "Assessment Innovation",
            "enhancedContent": {
              "focus": "Assessment innovation",
              "elements": [
                "portfolio",
                "authentic",
                "growth-mindset"
              ]
            },
            "timeCompleted": "2025-09-10T13:56:43.904Z",
            "qualityImprovement": 1.4298156504280368
          }
        ]
      },
      "metadata": {
        "created": "2023-09-23T12:00:00.000Z",
        "lastModified": "2025-09-10T13:56:43.904Z",
        "tags": [
          "social-studies",
          "year-11"
        ],
        "difficulty": 2,
        "estimatedDuration": 68
      }
    },
    {
      "id": "resource-00019",
      "title": "Year 11 Social Studies: Resource 19",
      "subject": "Social Studies",
      "yearLevel": "Year 11",
      "type": "lesson",
      "description": "Comprehensive lesson for Year 11 Social Studies learning",
      "culturalElements": 2,
      "currentPass": 4,
      "originalQuality": 6.481177374973759,
      "enhancement": {
        "passesCompleted": 4,
        "culturalAuthenticity": 9.865461444187316,
        "pedagogicalDepth": 8.834624519446256,
        "progressiveIndex": 8.606714145844625,
        "qualityScore": 13.655549319916162,
        "passes": [
          {
            "passNumber": 1,
            "kaiako": "Whaea Aroha Kaitiaki-ā-Taonga",
            "specialization": "Cultural Authenticity",
            "enhancedContent": {
              "focus": "Cultural authenticity",
              "elements": [
                "karakia",
                "tikanga",
                "Te Reo"
              ]
            },
            "timeCompleted": "2025-09-10T13:56:43.904Z",
            "qualityImprovement": 2.054332290889173
          },
          {
            "passNumber": 2,
            "kaiako": "Matua Rangi Akoranga-Hou",
            "specialization": "Progressive Pedagogy",
            "enhancedContent": {
              "focus": "Progressive pedagogy",
              "elements": [
                "project-based",
                "student-agency",
                "design-thinking"
              ]
            },
            "timeCompleted": "2025-09-10T13:56:43.904Z",
            "qualityImprovement": 2.106779073302369
          },
          {
            "passNumber": 3,
            "kaiako": "Whaea Mere Ako-Katoa",
            "specialization": "Universal Design",
            "enhancedContent": {
              "focus": "Universal design",
              "elements": [
                "multi-modal",
                "accessible",
                "inclusive"
              ]
            },
            "timeCompleted": "2025-09-10T13:56:43.904Z",
            "qualityImprovement": 1.5460089783422672
          },
          {
            "passNumber": 4,
            "kaiako": "Matua Tane Aromatawai-Tika",
            "specialization": "Assessment Innovation",
            "enhancedContent": {
              "focus": "Assessment innovation",
              "elements": [
                "portfolio",
                "authentic",
                "growth-mindset"
              ]
            },
            "timeCompleted": "2025-09-10T13:56:43.904Z",
            "qualityImprovement": 1.4672516024085918
          }
        ]
      },
      "metadata": {
        "created": "2023-12-16T11:00:00.000Z",
        "lastModified": "2025-09-10T13:56:43.904Z",
        "tags": [
          "social-studies",
          "year-11"
        ],
        "difficulty": 5,
        "estimatedDuration": 137
      }
    },
    {
      "id": "resource-00020",
      "title": "Year 8 Social Studies: Resource 20",
      "subject": "Social Studies",
      "yearLevel": "Year 8",
      "type": "multimedia",
      "description": "Comprehensive multimedia for Year 8 Social Studies learning",
      "culturalElements": 3,
      "currentPass": 4,
      "originalQuality": 6.995966789039455,
      "enhancement": {
        "passesCompleted": 4,
        "culturalAuthenticity": 9.71802175708193,
        "pedagogicalDepth": 9.086593531333135,
        "progressiveIndex": 8.959647637016896,
        "qualityScore": 15.030596901750291,
        "passes": [
          {
            "passNumber": 1,
            "kaiako": "Whaea Aroha Kaitiaki-ā-Taonga",
            "specialization": "Cultural Authenticity",
            "enhancedContent": {
              "focus": "Cultural authenticity",
              "elements": [
                "karakia",
                "tikanga",
                "Te Reo"
              ]
            },
            "timeCompleted": "2025-09-10T13:56:43.904Z",
            "qualityImprovement": 2.3606782899072156
          },
          {
            "passNumber": 2,
            "kaiako": "Matua Rangi Akoranga-Hou",
            "specialization": "Progressive Pedagogy",
            "enhancedContent": {
              "focus": "Progressive pedagogy",
              "elements": [
                "project-based",
                "student-agency",
                "design-thinking"
              ]
            },
            "timeCompleted": "2025-09-10T13:56:43.904Z",
            "qualityImprovement": 2.112364590691401
          },
          {
            "passNumber": 3,
            "kaiako": "Whaea Mere Ako-Katoa",
            "specialization": "Universal Design",
            "enhancedContent": {
              "focus": "Universal design",
              "elements": [
                "multi-modal",
                "accessible",
                "inclusive"
              ]
            },
            "timeCompleted": "2025-09-10T13:56:43.904Z",
            "qualityImprovement": 1.9722065232941097
          },
          {
            "passNumber": 4,
            "kaiako": "Matua Tane Aromatawai-Tika",
            "specialization": "Assessment Innovation",
            "enhancedContent": {
              "focus": "Assessment innovation",
              "elements": [
                "portfolio",
                "authentic",
                "growth-mindset"
              ]
            },
            "timeCompleted": "2025-09-10T13:56:43.904Z",
            "qualityImprovement": 1.5893807088181096
          }
        ]
      },
      "metadata": {
        "created": "2023-10-05T11:00:00.000Z",
        "lastModified": "2025-09-10T13:56:43.904Z",
        "tags": [
          "social-studies",
          "year-8"
        ],
        "difficulty": 1,
        "estimatedDuration": 114
      }
    }
  ]
}