{
  "batchId": "batch-353",
  "processedDate": "2025-09-10T13:57:21.466Z",
  "resourceCount": 10,
  "enhancedCount": 10,
  "resources": [
    {
      "id": "resource-03521",
      "title": "Year 12 English: Resource 3521",
      "subject": "English",
      "yearLevel": "Year 12",
      "type": "multimedia",
      "description": "Comprehensive multimedia for Year 12 English learning",
      "culturalElements": 3,
      "currentPass": 4,
      "originalQuality": 6.273560858353416,
      "enhancement": {
        "passesCompleted": 4,
        "culturalAuthenticity": 9.487243476299295,
        "pedagogicalDepth": 8.778976272204508,
        "progressiveIndex": 9.971186725158793,
        "qualityScore": 14.450960702556566,
        "passes": [
          {
            "passNumber": 1,
            "kaiako": "Whaea Aroha Kaitiaki-ā-Taonga",
            "specialization": "Cultural Authenticity",
            "enhancedContent": {
              "focus": "Cultural authenticity",
              "elements": [
                "karakia",
                "tikanga",
                "Te Reo"
              ]
            },
            "timeCompleted": "2025-09-10T13:57:21.466Z",
            "qualityImprovement": 2.2142553798298628
          },
          {
            "passNumber": 2,
            "kaiako": "Matua Rangi Akoranga-Hou",
            "specialization": "Progressive Pedagogy",
            "enhancedContent": {
              "focus": "Progressive pedagogy",
              "elements": [
                "project-based",
                "student-agency",
                "design-thinking"
              ]
            },
            "timeCompleted": "2025-09-10T13:57:21.466Z",
            "qualityImprovement": 2.1707870590532847
          },
          {
            "passNumber": 3,
            "kaiako": "Whaea Mere Ako-Katoa",
            "specialization": "Universal Design",
            "enhancedContent": {
              "focus": "Universal design",
              "elements": [
                "multi-modal",
                "accessible",
                "inclusive"
              ]
            },
            "timeCompleted": "2025-09-10T13:57:21.466Z",
            "qualityImprovement": 1.9477775220642455
          },
          {
            "passNumber": 4,
            "kaiako": "Matua Tane Aromatawai-Tika",
            "specialization": "Assessment Innovation",
            "enhancedContent": {
              "focus": "Assessment innovation",
              "elements": [
                "portfolio",
                "authentic",
                "growth-mindset"
              ]
            },
            "timeCompleted": "2025-09-10T13:57:21.466Z",
            "qualityImprovement": 1.8445798832557565
          }
        ]
      },
      "metadata": {
        "created": "2023-12-10T11:00:00.000Z",
        "lastModified": "2025-09-10T13:57:21.466Z",
        "tags": [
          "english",
          "year-12"
        ],
        "difficulty": 5,
        "estimatedDuration": 109
      }
    },
    {
      "id": "resource-03522",
      "title": "Year 13 English: Resource 3522",
      "subject": "English",
      "yearLevel": "Year 13",
      "type": "multimedia",
      "description": "Comprehensive multimedia for Year 13 English learning",
      "culturalElements": 1,
      "currentPass": 4,
      "originalQuality": 6.018535839873951,
      "enhancement": {
        "passesCompleted": 4,
        "culturalAuthenticity": 9.378715149875577,
        "pedagogicalDepth": 9.47043735955698,
        "progressiveIndex": 9.681778426638964,
        "qualityScore": 13.570111339329502,
        "passes": [
          {
            "passNumber": 1,
            "kaiako": "Whaea Aroha Kaitiaki-ā-Taonga",
            "specialization": "Cultural Authenticity",
            "enhancedContent": {
              "focus": "Cultural authenticity",
              "elements": [
                "karakia",
                "tikanga",
                "Te Reo"
              ]
            },
            "timeCompleted": "2025-09-10T13:57:21.466Z",
            "qualityImprovement": 2.1512139797869505
          },
          {
            "passNumber": 2,
            "kaiako": "Matua Rangi Akoranga-Hou",
            "specialization": "Progressive Pedagogy",
            "enhancedContent": {
              "focus": "Progressive pedagogy",
              "elements": [
                "project-based",
                "student-agency",
                "design-thinking"
              ]
            },
            "timeCompleted": "2025-09-10T13:57:21.466Z",
            "qualityImprovement": 1.9375448070637795
          },
          {
            "passNumber": 3,
            "kaiako": "Whaea Mere Ako-Katoa",
            "specialization": "Universal Design",
            "enhancedContent": {
              "focus": "Universal design",
              "elements": [
                "multi-modal",
                "accessible",
                "inclusive"
              ]
            },
            "timeCompleted": "2025-09-10T13:57:21.466Z",
            "qualityImprovement": 1.9986338588162362
          },
          {
            "passNumber": 4,
            "kaiako": "Matua Tane Aromatawai-Tika",
            "specialization": "Assessment Innovation",
            "enhancedContent": {
              "focus": "Assessment innovation",
              "elements": [
                "portfolio",
                "authentic",
                "growth-mindset"
              ]
            },
            "timeCompleted": "2025-09-10T13:57:21.466Z",
            "qualityImprovement": 1.4641828537885855
          }
        ]
      },
      "metadata": {
        "created": "2023-02-18T11:00:00.000Z",
        "lastModified": "2025-09-10T13:57:21.466Z",
        "tags": [
          "english",
          "year-13"
        ],
        "difficulty": 1,
        "estimatedDuration": 31
      }
    },
    {
      "id": "resource-03523",
      "title": "Year 12 English: Resource 3523",
      "subject": "English",
      "yearLevel": "Year 12",
      "type": "unit-plan",
      "description": "Comprehensive unit-plan for Year 12 English learning",
      "culturalElements": 1,
      "currentPass": 4,
      "originalQuality": 6.976925575462403,
      "enhancement": {
        "passesCompleted": 4,
        "culturalAuthenticity": 8.702940174602372,
        "pedagogicalDepth": 8.795095353497079,
        "progressiveIndex": 9.980304883118059,
        "qualityScore": 14.718229723599421,
        "passes": [
          {
            "passNumber": 1,
            "kaiako": "Whaea Aroha Kaitiaki-ā-Taonga",
            "specialization": "Cultural Authenticity",
            "enhancedContent": {
              "focus": "Cultural authenticity",
              "elements": [
                "karakia",
                "tikanga",
                "Te Reo"
              ]
            },
            "timeCompleted": "2025-09-10T13:57:21.466Z",
            "qualityImprovement": 2.3468018094423195
          },
          {
            "passNumber": 2,
            "kaiako": "Matua Rangi Akoranga-Hou",
            "specialization": "Progressive Pedagogy",
            "enhancedContent": {
              "focus": "Progressive pedagogy",
              "elements": [
                "project-based",
                "student-agency",
                "design-thinking"
              ]
            },
            "timeCompleted": "2025-09-10T13:57:21.466Z",
            "qualityImprovement": 1.9527654654563125
          },
          {
            "passNumber": 3,
            "kaiako": "Whaea Mere Ako-Katoa",
            "specialization": "Universal Design",
            "enhancedContent": {
              "focus": "Universal design",
              "elements": [
                "multi-modal",
                "accessible",
                "inclusive"
              ]
            },
            "timeCompleted": "2025-09-10T13:57:21.466Z",
            "qualityImprovement": 1.6572902014444795
          },
          {
            "passNumber": 4,
            "kaiako": "Matua Tane Aromatawai-Tika",
            "specialization": "Assessment Innovation",
            "enhancedContent": {
              "focus": "Assessment innovation",
              "elements": [
                "portfolio",
                "authentic",
                "growth-mindset"
              ]
            },
            "timeCompleted": "2025-09-10T13:57:21.466Z",
            "qualityImprovement": 1.784446671793909
          }
        ]
      },
      "metadata": {
        "created": "2023-10-18T11:00:00.000Z",
        "lastModified": "2025-09-10T13:57:21.466Z",
        "tags": [
          "english",
          "year-12"
        ],
        "difficulty": 5,
        "estimatedDuration": 32
      }
    },
    {
      "id": "resource-03524",
      "title": "Year 11 English: Resource 3524",
      "subject": "English",
      "yearLevel": "Year 11",
      "type": "assessment",
      "description": "Comprehensive assessment for Year 11 English learning",
      "culturalElements": 2,
      "currentPass": 4,
      "originalQuality": 5.711859070470184,
      "enhancement": {
        "passesCompleted": 4,
        "culturalAuthenticity": 9.545316254267995,
        "pedagogicalDepth": 8.623899460687348,
        "progressiveIndex": 8.645027711648744,
        "qualityScore": 13.696400166578838,
        "passes": [
          {
            "passNumber": 1,
            "kaiako": "Whaea Aroha Kaitiaki-ā-Taonga",
            "specialization": "Cultural Authenticity",
            "enhancedContent": {
              "focus": "Cultural authenticity",
              "elements": [
                "karakia",
                "tikanga",
                "Te Reo"
              ]
            },
            "timeCompleted": "2025-09-10T13:57:21.466Z",
            "qualityImprovement": 2.4165723388359446
          },
          {
            "passNumber": 2,
            "kaiako": "Matua Rangi Akoranga-Hou",
            "specialization": "Progressive Pedagogy",
            "enhancedContent": {
              "focus": "Progressive pedagogy",
              "elements": [
                "project-based",
                "student-agency",
                "design-thinking"
              ]
            },
            "timeCompleted": "2025-09-10T13:57:21.466Z",
            "qualityImprovement": 2.2684617980832
          },
          {
            "passNumber": 3,
            "kaiako": "Whaea Mere Ako-Katoa",
            "specialization": "Universal Design",
            "enhancedContent": {
              "focus": "Universal design",
              "elements": [
                "multi-modal",
                "accessible",
                "inclusive"
              ]
            },
            "timeCompleted": "2025-09-10T13:57:21.466Z",
            "qualityImprovement": 1.574394530738427
          },
          {
            "passNumber": 4,
            "kaiako": "Matua Tane Aromatawai-Tika",
            "specialization": "Assessment Innovation",
            "enhancedContent": {
              "focus": "Assessment innovation",
              "elements": [
                "portfolio",
                "authentic",
                "growth-mindset"
              ]
            },
            "timeCompleted": "2025-09-10T13:57:21.466Z",
            "qualityImprovement": 1.7251124284510833
          }
        ]
      },
      "metadata": {
        "created": "2023-11-04T11:00:00.000Z",
        "lastModified": "2025-09-10T13:57:21.466Z",
        "tags": [
          "english",
          "year-11"
        ],
        "difficulty": 4,
        "estimatedDuration": 62
      }
    },
    {
      "id": "resource-03525",
      "title": "Year 7 English: Resource 3525",
      "subject": "English",
      "yearLevel": "Year 7",
      "type": "lesson",
      "description": "Comprehensive lesson for Year 7 English learning",
      "culturalElements": 3,
      "currentPass": 4,
      "originalQuality": 5.601864676288928,
      "enhancement": {
        "passesCompleted": 4,
        "culturalAuthenticity": 8.509707531932984,
        "pedagogicalDepth": 9.386990869564986,
        "progressiveIndex": 9.471947646111444,
        "qualityScore": 13.31342016921667,
        "passes": [
          {
            "passNumber": 1,
            "kaiako": "Whaea Aroha Kaitiaki-ā-Taonga",
            "specialization": "Cultural Authenticity",
            "enhancedContent": {
              "focus": "Cultural authenticity",
              "elements": [
                "karakia",
                "tikanga",
                "Te Reo"
              ]
            },
            "timeCompleted": "2025-09-10T13:57:21.466Z",
            "qualityImprovement": 2.165407797632075
          },
          {
            "passNumber": 2,
            "kaiako": "Matua Rangi Akoranga-Hou",
            "specialization": "Progressive Pedagogy",
            "enhancedContent": {
              "focus": "Progressive pedagogy",
              "elements": [
                "project-based",
                "student-agency",
                "design-thinking"
              ]
            },
            "timeCompleted": "2025-09-10T13:57:21.466Z",
            "qualityImprovement": 1.8759433160002459
          },
          {
            "passNumber": 3,
            "kaiako": "Whaea Mere Ako-Katoa",
            "specialization": "Universal Design",
            "enhancedContent": {
              "focus": "Universal design",
              "elements": [
                "multi-modal",
                "accessible",
                "inclusive"
              ]
            },
            "timeCompleted": "2025-09-10T13:57:21.466Z",
            "qualityImprovement": 1.8034333533232518
          },
          {
            "passNumber": 4,
            "kaiako": "Matua Tane Aromatawai-Tika",
            "specialization": "Assessment Innovation",
            "enhancedContent": {
              "focus": "Assessment innovation",
              "elements": [
                "portfolio",
                "authentic",
                "growth-mindset"
              ]
            },
            "timeCompleted": "2025-09-10T13:57:21.466Z",
            "qualityImprovement": 1.8667710259721693
          }
        ]
      },
      "metadata": {
        "created": "2023-04-18T12:00:00.000Z",
        "lastModified": "2025-09-10T13:57:21.466Z",
        "tags": [
          "english",
          "year-7"
        ],
        "difficulty": 1,
        "estimatedDuration": 35
      }
    },
    {
      "id": "resource-03526",
      "title": "Year 12 English: Resource 3526",
      "subject": "English",
      "yearLevel": "Year 12",
      "type": "assessment",
      "description": "Comprehensive assessment for Year 12 English learning",
      "culturalElements": 5,
      "currentPass": 4,
      "originalQuality": 6.916787242552798,
      "enhancement": {
        "passesCompleted": 4,
        "culturalAuthenticity": 8.63202781085644,
        "pedagogicalDepth": 8.980007243899204,
        "progressiveIndex": 9.194732224066996,
        "qualityScore": 14.314395103980727,
        "passes": [
          {
            "passNumber": 1,
            "kaiako": "Whaea Aroha Kaitiaki-ā-Taonga",
            "specialization": "Cultural Authenticity",
            "enhancedContent": {
              "focus": "Cultural authenticity",
              "elements": [
                "karakia",
                "tikanga",
                "Te Reo"
              ]
            },
            "timeCompleted": "2025-09-10T13:57:21.466Z",
            "qualityImprovement": 2.28956125088867
          },
          {
            "passNumber": 2,
            "kaiako": "Matua Rangi Akoranga-Hou",
            "specialization": "Progressive Pedagogy",
            "enhancedContent": {
              "focus": "Progressive pedagogy",
              "elements": [
                "project-based",
                "student-agency",
                "design-thinking"
              ]
            },
            "timeCompleted": "2025-09-10T13:57:21.466Z",
            "qualityImprovement": 1.8944079165260015
          },
          {
            "passNumber": 3,
            "kaiako": "Whaea Mere Ako-Katoa",
            "specialization": "Universal Design",
            "enhancedContent": {
              "focus": "Universal design",
              "elements": [
                "multi-modal",
                "accessible",
                "inclusive"
              ]
            },
            "timeCompleted": "2025-09-10T13:57:21.466Z",
            "qualityImprovement": 1.647112902084077
          },
          {
            "passNumber": 4,
            "kaiako": "Matua Tane Aromatawai-Tika",
            "specialization": "Assessment Innovation",
            "enhancedContent": {
              "focus": "Assessment innovation",
              "elements": [
                "portfolio",
                "authentic",
                "growth-mindset"
              ]
            },
            "timeCompleted": "2025-09-10T13:57:21.466Z",
            "qualityImprovement": 1.566525791929182
          }
        ]
      },
      "metadata": {
        "created": "2023-12-24T11:00:00.000Z",
        "lastModified": "2025-09-10T13:57:21.466Z",
        "tags": [
          "english",
          "year-12"
        ],
        "difficulty": 2,
        "estimatedDuration": 85
      }
    },
    {
      "id": "resource-03527",
      "title": "Year 13 English: Resource 3527",
      "subject": "English",
      "yearLevel": "Year 13",
      "type": "multimedia",
      "description": "Comprehensive multimedia for Year 13 English learning",
      "culturalElements": 5,
      "currentPass": 4,
      "originalQuality": 6.787299532083255,
      "enhancement": {
        "passesCompleted": 4,
        "culturalAuthenticity": 9.18922717994735,
        "pedagogicalDepth": 8.707167898550612,
        "progressiveIndex": 9.04332559216056,
        "qualityScore": 13.951505951377111,
        "passes": [
          {
            "passNumber": 1,
            "kaiako": "Whaea Aroha Kaitiaki-ā-Taonga",
            "specialization": "Cultural Authenticity",
            "enhancedContent": {
              "focus": "Cultural authenticity",
              "elements": [
                "karakia",
                "tikanga",
                "Te Reo"
              ]
            },
            "timeCompleted": "2025-09-10T13:57:21.466Z",
            "qualityImprovement": 2.013284989101406
          },
          {
            "passNumber": 2,
            "kaiako": "Matua Rangi Akoranga-Hou",
            "specialization": "Progressive Pedagogy",
            "enhancedContent": {
              "focus": "Progressive pedagogy",
              "elements": [
                "project-based",
                "student-agency",
                "design-thinking"
              ]
            },
            "timeCompleted": "2025-09-10T13:57:21.466Z",
            "qualityImprovement": 1.8575146929319986
          },
          {
            "passNumber": 3,
            "kaiako": "Whaea Mere Ako-Katoa",
            "specialization": "Universal Design",
            "enhancedContent": {
              "focus": "Universal design",
              "elements": [
                "multi-modal",
                "accessible",
                "inclusive"
              ]
            },
            "timeCompleted": "2025-09-10T13:57:21.466Z",
            "qualityImprovement": 1.6226403800441709
          },
          {
            "passNumber": 4,
            "kaiako": "Matua Tane Aromatawai-Tika",
            "specialization": "Assessment Innovation",
            "enhancedContent": {
              "focus": "Assessment innovation",
              "elements": [
                "portfolio",
                "authentic",
                "growth-mindset"
              ]
            },
            "timeCompleted": "2025-09-10T13:57:21.466Z",
            "qualityImprovement": 1.6707663572162816
          }
        ]
      },
      "metadata": {
        "created": "2023-12-07T11:00:00.000Z",
        "lastModified": "2025-09-10T13:57:21.466Z",
        "tags": [
          "english",
          "year-13"
        ],
        "difficulty": 4,
        "estimatedDuration": 60
      }
    },
    {
      "id": "resource-03528",
      "title": "Year 12 English: Resource 3528",
      "subject": "English",
      "yearLevel": "Year 12",
      "type": "multimedia",
      "description": "Comprehensive multimedia for Year 12 English learning",
      "culturalElements": 1,
      "currentPass": 4,
      "originalQuality": 6.681153849200121,
      "enhancement": {
        "passesCompleted": 4,
        "culturalAuthenticity": 8.774766602187793,
        "pedagogicalDepth": 9.206074878403568,
        "progressiveIndex": 9.494675934070479,
        "qualityScore": 14.604048615277334,
        "passes": [
          {
            "passNumber": 1,
            "kaiako": "Whaea Aroha Kaitiaki-ā-Taonga",
            "specialization": "Cultural Authenticity",
            "enhancedContent": {
              "focus": "Cultural authenticity",
              "elements": [
                "karakia",
                "tikanga",
                "Te Reo"
              ]
            },
            "timeCompleted": "2025-09-10T13:57:21.466Z",
            "qualityImprovement": 2.4093343908420684
          },
          {
            "passNumber": 2,
            "kaiako": "Matua Rangi Akoranga-Hou",
            "specialization": "Progressive Pedagogy",
            "enhancedContent": {
              "focus": "Progressive pedagogy",
              "elements": [
                "project-based",
                "student-agency",
                "design-thinking"
              ]
            },
            "timeCompleted": "2025-09-10T13:57:21.466Z",
            "qualityImprovement": 1.9244666396126733
          },
          {
            "passNumber": 3,
            "kaiako": "Whaea Mere Ako-Katoa",
            "specialization": "Universal Design",
            "enhancedContent": {
              "focus": "Universal design",
              "elements": [
                "multi-modal",
                "accessible",
                "inclusive"
              ]
            },
            "timeCompleted": "2025-09-10T13:57:21.466Z",
            "qualityImprovement": 1.8218414361820126
          },
          {
            "passNumber": 4,
            "kaiako": "Matua Tane Aromatawai-Tika",
            "specialization": "Assessment Innovation",
            "enhancedContent": {
              "focus": "Assessment innovation",
              "elements": [
                "portfolio",
                "authentic",
                "growth-mindset"
              ]
            },
            "timeCompleted": "2025-09-10T13:57:21.466Z",
            "qualityImprovement": 1.7672522994404591
          }
        ]
      },
      "metadata": {
        "created": "2023-12-25T11:00:00.000Z",
        "lastModified": "2025-09-10T13:57:21.466Z",
        "tags": [
          "english",
          "year-12"
        ],
        "difficulty": 1,
        "estimatedDuration": 60
      }
    },
    {
      "id": "resource-03529",
      "title": "Year 8 English: Resource 3529",
      "subject": "English",
      "yearLevel": "Year 8",
      "type": "lesson",
      "description": "Comprehensive lesson for Year 8 English learning",
      "culturalElements": 2,
      "currentPass": 4,
      "originalQuality": 5.826148658319981,
      "enhancement": {
        "passesCompleted": 4,
        "culturalAuthenticity": 8.957565280269552,
        "pedagogicalDepth": 8.596116868236031,
        "progressiveIndex": 8.78084721156789,
        "qualityScore": 13.74878544622253,
        "passes": [
          {
            "passNumber": 1,
            "kaiako": "Whaea Aroha Kaitiaki-ā-Taonga",
            "specialization": "Cultural Authenticity",
            "enhancedContent": {
              "focus": "Cultural authenticity",
              "elements": [
                "karakia",
                "tikanga",
                "Te Reo"
              ]
            },
            "timeCompleted": "2025-09-10T13:57:21.466Z",
            "qualityImprovement": 2.36344137306739
          },
          {
            "passNumber": 2,
            "kaiako": "Matua Rangi Akoranga-Hou",
            "specialization": "Progressive Pedagogy",
            "enhancedContent": {
              "focus": "Progressive pedagogy",
              "elements": [
                "project-based",
                "student-agency",
                "design-thinking"
              ]
            },
            "timeCompleted": "2025-09-10T13:57:21.466Z",
            "qualityImprovement": 2.12323740205325
          },
          {
            "passNumber": 3,
            "kaiako": "Whaea Mere Ako-Katoa",
            "specialization": "Universal Design",
            "enhancedContent": {
              "focus": "Universal design",
              "elements": [
                "multi-modal",
                "accessible",
                "inclusive"
              ]
            },
            "timeCompleted": "2025-09-10T13:57:21.466Z",
            "qualityImprovement": 1.9676118455840799
          },
          {
            "passNumber": 4,
            "kaiako": "Matua Tane Aromatawai-Tika",
            "specialization": "Assessment Innovation",
            "enhancedContent": {
              "focus": "Assessment innovation",
              "elements": [
                "portfolio",
                "authentic",
                "growth-mindset"
              ]
            },
            "timeCompleted": "2025-09-10T13:57:21.466Z",
            "qualityImprovement": 1.4683461671978284
          }
        ]
      },
      "metadata": {
        "created": "2023-08-18T12:00:00.000Z",
        "lastModified": "2025-09-10T13:57:21.466Z",
        "tags": [
          "english",
          "year-8"
        ],
        "difficulty": 1,
        "estimatedDuration": 89
      }
    },
    {
      "id": "resource-03530",
      "title": "Year 8 English: Resource 3530",
      "subject": "English",
      "yearLevel": "Year 8",
      "type": "assessment",
      "description": "Comprehensive assessment for Year 8 English learning",
      "culturalElements": 3,
      "currentPass": 4,
      "originalQuality": 6.569420619627788,
      "enhancement": {
        "passesCompleted": 4,
        "culturalAuthenticity": 9.396419742831382,
        "pedagogicalDepth": 9.483025780515526,
        "progressiveIndex": 8.65107312538093,
        "qualityScore": 14.650293916582692,
        "passes": [
          {
            "passNumber": 1,
            "kaiako": "Whaea Aroha Kaitiaki-ā-Taonga",
            "specialization": "Cultural Authenticity",
            "enhancedContent": {
              "focus": "Cultural authenticity",
              "elements": [
                "karakia",
                "tikanga",
                "Te Reo"
              ]
            },
            "timeCompleted": "2025-09-10T13:57:21.466Z",
            "qualityImprovement": 2.3232809067813025
          },
          {
            "passNumber": 2,
            "kaiako": "Matua Rangi Akoranga-Hou",
            "specialization": "Progressive Pedagogy",
            "enhancedContent": {
              "focus": "Progressive pedagogy",
              "elements": [
                "project-based",
                "student-agency",
                "design-thinking"
              ]
            },
            "timeCompleted": "2025-09-10T13:57:21.466Z",
            "qualityImprovement": 2.189187532746882
          },
          {
            "passNumber": 3,
            "kaiako": "Whaea Mere Ako-Katoa",
            "specialization": "Universal Design",
            "enhancedContent": {
              "focus": "Universal design",
              "elements": [
                "multi-modal",
                "accessible",
                "inclusive"
              ]
            },
            "timeCompleted": "2025-09-10T13:57:21.466Z",
            "qualityImprovement": 1.85372822542323
          },
          {
            "passNumber": 4,
            "kaiako": "Matua Tane Aromatawai-Tika",
            "specialization": "Assessment Innovation",
            "enhancedContent": {
              "focus": "Assessment innovation",
              "elements": [
                "portfolio",
                "authentic",
                "growth-mindset"
              ]
            },
            "timeCompleted": "2025-09-10T13:57:21.466Z",
            "qualityImprovement": 1.7146766320034883
          }
        ]
      },
      "metadata": {
        "created": "2023-01-11T11:00:00.000Z",
        "lastModified": "2025-09-10T13:57:21.466Z",
        "tags": [
          "english",
          "year-8"
        ],
        "difficulty": 5,
        "estimatedDuration": 61
      }
    }
  ]
}